LICENSE
README.md
pyproject.toml
setup.py
qickit/__init__.py
qickit.egg-info/PKG-INFO
qickit.egg-info/SOURCES.txt
qickit.egg-info/dependency_links.txt
qickit.egg-info/requires.txt
qickit.egg-info/top_level.txt
qickit/backend/__init__.py
qickit/backend/backend.py
qickit/circuit/__init__.py
qickit/circuit/circuit.py
qickit/circuit/circuit_log.py
qickit/circuit/circuit_utils.py
qickit/circuit/cirqcircuit.py
qickit/circuit/cudaqcircuit_temp.py
qickit/circuit/pennylanecircuit.py
qickit/circuit/qiskitcircuit.py
qickit/circuit/tketcircuit.py
qickit/circuit/dag/__init__.py
qickit/circuit/dag/dagcircuit.py
qickit/circuit/dag/dagnode.py
qickit/circuit/from_framework/__init__.py
qickit/circuit/from_framework/from_cirq.py
qickit/circuit/from_framework/from_framework.py
qickit/circuit/from_framework/from_qasm.py
qickit/circuit/from_framework/from_qiskit.py
qickit/circuit/from_framework/from_tket.py
qickit/circuit/gate_matrix/__init__.py
qickit/circuit/gate_matrix/controlled_qubit_gates.py
qickit/circuit/gate_matrix/gate.py
qickit/circuit/gate_matrix/single_qubit_gates.py
qickit/compiler/__init__.py
qickit/compiler/compiler.py
qickit/optimizer/__init__.py
qickit/optimizer/optimizer.py
qickit/optimizer/qiskit_transpiler.py
qickit/optimizer/tket2optimizer.py
qickit/predicates/__init__.py
qickit/predicates/predicates.py
qickit/primitives/__init__.py
qickit/primitives/bra.py
qickit/primitives/ket.py
qickit/primitives/operator.py
qickit/synthesis/__init__.py
qickit/synthesis/gate_decompositions/__init__.py
qickit/synthesis/gate_decompositions/one_qubit_decomposition.py
qickit/synthesis/gate_decompositions/multi_controlled_decomposition/__init__.py
qickit/synthesis/gate_decompositions/multi_controlled_decomposition/mcsu2_real_diagonal.py
qickit/synthesis/gate_decompositions/multi_controlled_decomposition/mcx_vchain.py
qickit/synthesis/statepreparation/__init__.py
qickit/synthesis/statepreparation/isometry.py
qickit/synthesis/statepreparation/mottonen.py
qickit/synthesis/statepreparation/shende.py
qickit/synthesis/statepreparation/statepreparation.py
qickit/synthesis/statepreparation/statepreparation_utils.py
