Metadata-Version: 2.1
Name: qickit
Version: 0.0.0
Summary: Qickit is an agnostic gate-based circuit SDK, providing an integrated interface for using any supported quantum circuit framework seamlessly.
Author: Amir Ali Malekani Nezhad
Author-email: Amir Ali Malekani Nezhad <amiralimlk07@gmail.com>
Maintainer-email: Amir Ali Malekani Nezhad <amiralimlk07@gmail.com>
License:                                  Apache License
Project-URL: Repository, https://github.com/qualition/qickit.git
Project-URL: Bug Tracker, https://github.com/qualition/qickit/issues
Keywords: quantum computing,quantum circuit,quantum compiler
Classifier: Development Status :: 3 - Alpha
Classifier: Programming Language :: Python :: 3.10
Classifier: Programming Language :: Python :: 3.11
Classifier: Programming Language :: Python :: 3.12
Classifier: Operating System :: OS Independent
Requires-Python: >=3.10,<=3.12
License-File: LICENSE
Requires-Dist: cirq-core==1.4.1
Requires-Dist: mypy==1.13.0
Requires-Dist: numpy~=1.23
Requires-Dist: pennylane==0.39.0
Requires-Dist: pytket==1.34.0
Requires-Dist: pytket-qiskit==0.62.0
Requires-Dist: pytket-cirq==0.39.0
Requires-Dist: pytest==8.2.2
Requires-Dist: pytest-mock==3.14.0
Requires-Dist: qiskit==1.3.1
Requires-Dist: qiskit_aer==0.15.1
Requires-Dist: qiskit_ibm_runtime==0.34.0
Requires-Dist: qiskit-transpiler-service==0.4.14
Requires-Dist: quimb==1.9.0
Requires-Dist: ruff==0.8.3
Requires-Dist: tket2==0.6.0
